effect/__init__.py
effect/effect.py
effect/identity.py
effect/py.typed
effect/state_transition.py
effect/sugar.py
effectt-0.2.0.dist-info/METADATA
effectt-0.2.0.dist-info/WHEEL
effectt-0.2.0.dist-info/licenses/LICENSE
effectt-0.2.0.dist-info/RECORD
