Metadata-Version: 2.4
Name: effectt
Version: 0.2.0
Summary: Change tracking library for frozen dataclasses
Project-URL: Repository, https://github.com/emptybutton/effect
Author-email: Alexander Smolin <88573504+emptybutton@users.noreply.github.com>
License:                                  Apache License
License-File: LICENSE
Requires-Python: >=3.13
Provides-Extra: dev
Requires-Dist: dirty-equals==0.8.0; extra == 'dev'
Requires-Dist: mypy[faster-cache]==1.15.0; extra == 'dev'
Requires-Dist: pytest-asyncio==0.25.3; extra == 'dev'
Requires-Dist: pytest-cov==6.0.0; extra == 'dev'
Requires-Dist: pytest==8.3.4; extra == 'dev'
Requires-Dist: ruff==0.9.7; extra == 'dev'
